midgard_py/__init__.py
midgard_py/midgard_api.py
midgard_py/models/__init__.py
midgard_py/models/midgard_models_health.py
midgard_py/models/midgard_models_pool.py
midgard_py/tests/__init__.py
midgard_py/tests/test_health.py
midgard_py/tests/test_pool.py
midgard_py-0.0.1.dist-info/LICENSE.txt
midgard_py-0.0.1.dist-info/METADATA
midgard_py-0.0.1.dist-info/WHEEL
midgard_py-0.0.1.dist-info/top_level.txt
midgard_py-0.0.1.dist-info/RECORD
