Metadata-Version: 2.1
Name: midgard-py
Version: 0.0.1
Summary: UNKNOWN
Home-page: https://github.com/jpleorx/midgard-py
Author: Leo Ertuna
Author-email: leo.ertuna@gmail.com
License: Creative Commons Attribution-NonCommercial-NoDerivatives 4.0 International Public License
Download-URL: https://pypi.org/project/midgard-py/
Platform: UNKNOWN
License-File: LICENSE.txt
Requires-Dist: pydantic
Requires-Dist: requests
